peekStock/__init__.py
peekStock/app.py
peekStock/crawlerHelper.py
peekStock-0.0.1.dist-info/LICENSE.txt
peekStock-0.0.1.dist-info/METADATA
peekStock-0.0.1.dist-info/WHEEL
peekStock-0.0.1.dist-info/top_level.txt
peekStock-0.0.1.dist-info/RECORD
