Metadata-Version: 2.1
Name: peekStock
Version: 0.0.1
Summary: A easy tool to track your stock on your work
Home-page: https://github.com/Nancy-Hsu/Peek-Stock/tree/main
Author: Nancy Hsu
Author-email: yutinghsu0411@gmail.com
Classifier: Programming Language :: Python :: 3
Classifier: License :: OSI Approved :: MIT License
Classifier: Operating System :: OS Independent
License-File: LICENSE.txt
